{
   "nodes": [{
      "name": "Aiton Elementary School",
      "node": 0
   }, {
      "name": "Bancroft Elementary School",
      "node": 1
   }, {
      "name": "Barnard Elementary School",
      "node": 2
   }, {
      "name": "Beers Elementary School",
      "node": 3
   }, {
      "name": "Brent Elementary School",
      "node": 4
   }, {
      "name": "Burroughs Education Campus",
      "node": 5
   }, {
      "name": "Burrville Elementary School",
      "node": 6
   }, {
      "name": "C.W. Harris Elementary School",
      "node": 7
   }, {
      "name": "Cleveland Elementary School",
      "node": 8
   }, {
      "name": "Drew Elementary School",
      "node": 9
   }, {
      "name": "Eaton Elementary School",
      "node": 10
   }, {
      "name": "Garfield Elementary School",
      "node": 11
   }, {
      "name": "Garrison Elementary School",
      "node": 12
   }, {
      "name": "Hendley Elementary School",
      "node": 13
   }, {
      "name": "Houston Elementary School",
      "node": 14
   }, {
      "name": "Hyde-Addison Elementary School",
      "node": 15
   }, {
      "name": "J.O. Wilson Elementary School",
      "node": 16
   }, {
      "name": "Janney Elementary School",
      "node": 17
   }, {
      "name": "Ketcham Elementary School",
      "node": 18
   }, {
      "name": "Key Elementary School",
      "node": 19
   }, {
      "name": "Kimball Elementary School",
      "node": 20
   }, {
      "name": "Lafayette Elementary School",
      "node": 21
   }, {
      "name": "Langdon Education Campus",
      "node": 22
   }, {
      "name": "Langley Education Campus",
      "node": 23
   }, {
      "name": "Leckie Elementary School",
      "node": 24
   }, {
      "name": "Ludlow-Taylor Elementary School",
      "node": 25
   }, {
      "name": "Mann Elementary School",
      "node": 26
   }, {
      "name": "Marie Reed Elementary School",
      "node": 27
   }, {
      "name": "Maury Elementary School",
      "node": 28
   }, {
      "name": "Moten Elementary School",
      "node": 29
   }, {
      "name": "Murch Elementary School",
      "node": 30
   }, {
      "name": "Nalle Elementary School",
      "node": 31
   }, {
      "name": "Noyes Education Campus",
      "node": 32
   }, {
      "name": "Old Miner",
      "node": 33
   }, {
      "name": "Orr Elementary School",
      "node": 34
   }, {
      "name": "Patterson Elementary School",
      "node": 35
   }, {
      "name": "Payne Elementary School",
      "node": 36
   }, {
      "name": "Peabody Elementary School",
      "node": 37
   }, {
      "name": "Plummer Elementary School",
      "node": 38
   }, {
      "name": "Powell Elementary School",
      "node": 39
   }, {
      "name": "Ross Elementary School",
      "node": 40
   }, {
      "name": "Savoy Elementary School",
      "node": 41
   }, {
      "name": "Seaton Elementary School",
      "node": 42
   }, {
      "name": "Shepherd Elementary School",
      "node": 43
   }, {
      "name": "Simon Elementary School",
      "node": 44
   }, {
      "name": "Smothers Elementary School",
      "node": 45
   }, {
      "name": "Stanton Elementary School",
      "node": 46
   }, {
      "name": "Stoddert Elementary School",
      "node": 47
   }, {
      "name": "Thomas Elementary School",
      "node": 48
   }, {
      "name": "Thomson Elementary School",
      "node": 49
   }, {
      "name": "Tubman Elementary School",
      "node": 50
   }, {
      "name": "Turner Elementary School",
      "node": 51
   }, {
      "name": "Tyler Elementary School",
      "node": 52
   }, {
      "name": "Watkins Elementary School",
      "node": 53
   }, {
      "name": "Hearst Elementary School",
      "node": 54
   }, {
      "name": "Van Ness ES",
      "node": 55
   }, {
      "name": "Amidon-Bowen Elementary School",
      "node": 56
   }, {
      "name": "H.D. Cooke Elementary School",
      "node": 57
   }, {
      "name": "King Elementary School",
      "node": 58
   }, {
      "name": "Bruce-Monroe Elementary School @ Park View",
      "node": 59
   }, {
      "name": "Oyster-Adams Bilingual School (Oyster)",
      "node": 60
   }, {
      "name": "Brookland Education Campus @ Bunker Hill",
      "node": 61
   }, {
      "name": "Malcolm X Elementary School",
      "node": 62
   }, {
      "name": "Prospect Learning Center",
      "node": 63
   }, {
      "name": "Deal Middle School",
      "node": 64
   }, {
      "name": "Eliot-Hine Middle School",
      "node": 65
   }, {
      "name": "Hardy Middle School",
      "node": 66
   }, {
      "name": "Hart Middle School",
      "node": 67
   }, {
      "name": "Jefferson Middle School",
      "node": 68
   }, {
      "name": "Kelly Miller Middle School",
      "node": 69
   }, {
      "name": "Kramer Middle School",
      "node": 70
   }, {
      "name": "Sousa Middle School",
      "node": 71
   }, {
      "name": "John Hayden Johnson Middle School",
      "node": 72
   }, {
      "name": "Stuart-Hobson Middle School",
      "node": 73
   }, {
      "name": "Brookland MS",
      "node": 74
   }, {
      "name": "Oyster-Adams Bilingual School (Adams)",
      "node": 75
   }, {
      "name": "Brightwood Education Campus",
      "node": 76
   }, {
      "name": "Browne Education Campus",
      "node": 77
   }, {
      "name": "Raymond Education Campus",
      "node": 78
   }, {
      "name": "Takoma Education Campus",
      "node": 79
   }, {
      "name": "Truesdell Education Campus",
      "node": 80
   }, {
      "name": "Walker-Jones Education Campus",
      "node": 81
   }, {
      "name": "Wheatley Education Campus",
      "node": 82
   }, {
      "name": "Whittier Education Campus",
      "node": 83
   }, {
      "name": "West Education Campus",
      "node": 84
   }, {
      "name": "Francis-Stevens Education Campus",
      "node": 85
   }, {
      "name": "LaSalle-Backus Education Campus",
      "node": 86
   }, {
      "name": "Capitol Hill Montessori School @ Logan",
      "node": 87
   }, {
      "name": "Anacostia High School",
      "node": 88
   }, {
      "name": "Coolidge High School",
      "node": 89
   }, {
      "name": "Eastern High School",
      "node": 90
   }, {
      "name": "Ellington School of the Arts",
      "node": 91
   }, {
      "name": "Phelps Architecture, Construction, and Engineering High School",
      "node": 92
   }, {
      "name": "School Without Walls High School",
      "node": 93
   }, {
      "name": "Wilson High School",
      "node": 94
   }, {
      "name": "Benjamin Banneker High School",
      "node": 95
   }, {
      "name": "Woodson, H.D. HS",
      "node": 96
   }, {
      "name": "Roosevelt High School",
      "node": 97
   }, {
      "name": "McKinley Technology High School",
      "node": 98
   }, {
      "name": "Roosevelt High School",
      "node": 99
   }],
   "links": [{
      "source": 0,
      "target": 64
   }, {
      "source": 1,
      "target": 64
   }, {
      "source": 2,
      "target": 64
   }, {
      "source": 3,
      "target": 64
   }, {
      "source": 4,
      "target": 64
   }, {
      "source": 5,
      "target": 64
   }, {
      "source": 6,
      "target": 64
   }, {
      "source": 7,
      "target": 64
   }, {
      "source": 8,
      "target": 64
   }, {
      "source": 9,
      "target": 64
   }, {
      "source": 10,
      "target": 64
   }, {
      "source": 11,
      "target": 64
   }, {
      "source": 12,
      "target": 64
   }, {
      "source": 13,
      "target": 64
   }, {
      "source": 14,
      "target": 64
   }, {
      "source": 15,
      "target": 64
   }, {
      "source": 16,
      "target": 64
   }, {
      "source": 17,
      "target": 64
   }, {
      "source": 18,
      "target": 64
   }, {
      "source": 19,
      "target": 64
   }, {
      "source": 20,
      "target": 64
   }, {
      "source": 21,
      "target": 64
   }, {
      "source": 22,
      "target": 64
   }, {
      "source": 23,
      "target": 64
   }, {
      "source": 24,
      "target": 64
   }, {
      "source": 25,
      "target": 64
   }, {
      "source": 26,
      "target": 64
   }, {
      "source": 27,
      "target": 64
   }, {
      "source": 28,
      "target": 64
   }, {
      "source": 29,
      "target": 64
   }, {
      "source": 30,
      "target": 64
   }, {
      "source": 31,
      "target": 64
   }, {
      "source": 32,
      "target": 64
   }, {
      "source": 33,
      "target": 64
   }, {
      "source": 34,
      "target": 64
   }, {
      "source": 35,
      "target": 64
   }, {
      "source": 36,
      "target": 64
   }, {
      "source": 37,
      "target": 64
   }, {
      "source": 38,
      "target": 64
   }, {
      "source": 39,
      "target": 64
   }, {
      "source": 40,
      "target": 64
   }, {
      "source": 41,
      "target": 64
   }, {
      "source": 42,
      "target": 64
   }, {
      "source": 43,
      "target": 64
   }, {
      "source": 44,
      "target": 64
   }, {
      "source": 45,
      "target": 64
   }, {
      "source": 46,
      "target": 64
   }, {
      "source": 47,
      "target": 64
   }, {
      "source": 48,
      "target": 64
   }, {
      "source": 49,
      "target": 64
   }, {
      "source": 50,
      "target": 64
   }, {
      "source": 51,
      "target": 64
   }, {
      "source": 52,
      "target": 64
   }, {
      "source": 53,
      "target": 64
   }, {
      "source": 54,
      "target": 64
   }, {
      "source": 55,
      "target": 64
   }, {
      "source": 56,
      "target": 64
   }, {
      "source": 57,
      "target": 64
   }, {
      "source": 58,
      "target": 64
   }, {
      "source": 59,
      "target": 64
   }, {
      "source": 60,
      "target": 64
   }, {
      "source": 61,
      "target": 64
   }, {
      "source": 62,
      "target": 64
   }, {
      "source": 63,
      "target": 64
   }, {
      "source": 100,
      "target": 64,
      "value": 10
   }, {
      "source": 101,
      "target": 64,
      "value": 10
   }, {
      "source": 102,
      "target": 64,
      "value": 10
   }, {
      "source": 103,
      "target": 64,
      "value": 10
   }, {
      "source": 104,
      "target": 64,
      "value": 10
   }, {
      "source": 105,
      "target": 64,
      "value": 10
   }, {
      "source": 106,
      "target": 64,
      "value": 10
   }, {
      "source": 107,
      "target": 64,
      "value": 10
   }, {
      "source": 108,
      "target": 64,
      "value": 10
   }, {
      "source": 109,
      "target": 64,
      "value": 10
   }, {
      "source": 110,
      "target": 64,
      "value": 10
   }, {
      "source": 111,
      "target": 64,
      "value": 10
   }, {
      "source": 112,
      "target": 0,
      "value": 10
   }, {
      "source": 113,
      "target": 1,
      "value": 10
   }, {
      "source": 114,
      "target": 2,
      "value": 10
   }, {
      "source": 115,
      "target": 3,
      "value": 10
   }, {
      "source": 116,
      "target": 4,
      "value": 10
   }, {
      "source": 117,
      "target": 5,
      "value": 10
   }, {
      "source": 118,
      "target": 6,
      "value": 10
   }, {
      "source": 119,
      "target": 7,
      "value": 10
   }, {
      "source": 120,
      "target": 8,
      "value": 10
   }, {
      "source": 121,
      "target": 9,
      "value": 10
   }, {
      "source": 122,
      "target": 10,
      "value": 10
   }, {
      "source": 123,
      "target": 11,
      "value": 10
   }, {
      "source": 124,
      "target": 0,
      "value": 10
   }, {
      "source": 125,
      "target": 1,
      "value": 10
   }, {
      "source": 126,
      "target": 2,
      "value": 10
   }, {
      "source": 127,
      "target": 3,
      "value": 10
   }, {
      "source": 128,
      "target": 4,
      "value": 10
   }, {
      "source": 129,
      "target": 5,
      "value": 10
   }, {
      "source": 130,
      "target": 6,
      "value": 10
   }, {
      "source": 131,
      "target": 7,
      "value": 10
   }, {
      "source": 132,
      "target": 8,
      "value": 10
   }, {
      "source": 133,
      "target": 9,
      "value": 10
   }, {
      "source": 134,
      "target": 10,
      "value": 10
   }, {
      "source": 135,
      "target": 11,
      "value": 10
   }]
}